le.py
le-1.0.16.dist-info/DESCRIPTION.rst
le-1.0.16.dist-info/METADATA
le-1.0.16.dist-info/RECORD
le-1.0.16.dist-info/WHEEL
le-1.0.16.dist-info/entry_points.txt
le-1.0.16.dist-info/metadata.json
le-1.0.16.dist-info/top_level.txt
